{"cameraMode":{"drawMode":0,"name":"Shaded","section":"Shading Mode"},"sceneLighting":false,"audioPlay":false,"sceneViewState":{"showFog":true,"showMaterialUpdate":false,"showSkybox":false,"showFlares":true,"showImageEffects":true,"showParticleSystems":true},"in2DMode":false,"pivot":{"x":-4.358715057373047,"y":1.0914664268493653,"z":30.123533248901368},"rotation":{"x":-0.38395336270332339,"y":0.21969512104988099,"z":-0.09452096372842789,"w":-0.8918718099594116},"size":11.487900733947754,"orthographic":false}